achibdatalib/dist/datalib-0.1.0.tar.gz
achibdatalib/docs/build/doctrees/environment.pickle
achibdatalib/docs/build/doctrees/index.doctree
achibdatalib/docs/build/doctrees/modules.doctree
achibdatalib/docs/build/html/.buildinfo
achibdatalib/docs/build/html/_sources/index.rst.txt
achibdatalib/docs/build/html/_sources/modules.rst.txt
achibdatalib/docs/build/html/_static/_sphinx_javascript_frameworks_compat.js
achibdatalib/docs/build/html/_static/alabaster.css
achibdatalib/docs/build/html/_static/basic.css
achibdatalib/docs/build/html/_static/custom.css
achibdatalib/docs/build/html/_static/doctools.js
achibdatalib/docs/build/html/_static/documentation_options.js
achibdatalib/docs/build/html/_static/file.png
achibdatalib/docs/build/html/_static/jquery-3.6.0.js
achibdatalib/docs/build/html/_static/jquery.js
achibdatalib/docs/build/html/_static/language_data.js
achibdatalib/docs/build/html/_static/minus.png
achibdatalib/docs/build/html/_static/plus.png
achibdatalib/docs/build/html/_static/pygments.css
achibdatalib/docs/build/html/_static/searchtools.js
achibdatalib/docs/build/html/_static/sphinx_highlight.js
achibdatalib/docs/build/html/_static/underscore-1.13.1.js
achibdatalib/docs/build/html/_static/underscore.js
achibdatalib/docs/build/html/genindex.html
achibdatalib/docs/build/html/index.html
achibdatalib/docs/build/html/modules.html
achibdatalib/docs/build/html/objects.inv
achibdatalib/docs/build/html/py-modindex.html
achibdatalib/docs/build/html/search.html
achibdatalib/docs/build/html/searchindex.js
achibdatalib/docs/make.bat
achibdatalib/docs/Makefile
achibdatalib/docs/source/conf.py
achibdatalib/docs/source/index.rst
achibdatalib/docs/source/modules.rst
achibdatalib/src/__init__.py
achibdatalib/src/analysis/__init__.py
achibdatalib/src/analysis/advanced_analysis.py
achibdatalib/src/analysis/exploratory_analysis.py
achibdatalib/src/data_lib.py
achibdatalib/src/data_processing.py
achibdatalib/src/models/__init__.py
achibdatalib/src/models/classification.py
achibdatalib-0.1.0.dist-info/METADATA
achibdatalib-0.1.0.dist-info/WHEEL
achibdatalib-0.1.0.dist-info/RECORD
