Metadata-Version: 2.1
Name: achibdatalib
Version: 0.1.0
Summary: A library for data manipulation and analysis.
License: MIT
Author: Your Name
Author-email: you@example.com
Requires-Python: >=3.9
Classifier: License :: OSI Approved :: MIT License
Classifier: Programming Language :: Python :: 3
Classifier: Programming Language :: Python :: 3.9
Classifier: Programming Language :: Python :: 3.10
Classifier: Programming Language :: Python :: 3.11
Classifier: Programming Language :: Python :: 3.12
Classifier: Programming Language :: Python :: 3.13
Requires-Dist: numpy (>=1.21.0,<2.0.0)
Requires-Dist: pandas (>=1.3.0,<2.0.0)
Requires-Dist: pytest (>=6.2.4,<7.0.0)
Requires-Dist: scikit-learn (>=0.24.2,<0.25.0)
